{"cameraMode":{"drawMode":0,"name":"Shaded","section":"Shading Mode"},"sceneLighting":false,"audioPlay":false,"sceneViewState":{"showFog":true,"showMaterialUpdate":false,"showSkybox":false,"showFlares":true,"showImageEffects":true,"showParticleSystems":true},"in2DMode":false,"pivot":{"x":-8.041857719421387,"y":2.455142021179199,"z":6.617837905883789},"rotation":{"x":0.0624430887401104,"y":-0.726998507976532,"z":0.06670664250850678,"w":0.6805330514907837},"size":4.537010669708252,"orthographic":false}